{"options":{"chapters":true},"entries":[{"caption":"Portfolios of two risky assets and risk-free saving and borrowing","key":"fig-two-asset-plus_rf_saveborrow","order":{"number":8,"section":[2,3,2,0,0,0,0]}},{"caption":"","key":"eq-n-asset-variance","order":{"number":8,"section":[2,1,1,0,0,0,0]}},{"caption":"2.5 Appendix: The Portfolio Class in Python","key":"sec-portfolio-class","order":{"number":10,"section":[2,5,0,0,0,0,0]}},{"caption":"","key":"eq-2asset-return","order":{"number":3,"section":[2,1,0,0,0,0,0]}},{"caption":"","key":"eq-n-asset-expret","order":{"number":7,"section":[2,1,1,0,0,0,0]}},{"caption":"","key":"eq-expret-rf-risky","order":{"number":15,"section":[2,3,1,0,0,0,0]}},{"caption":"","key":"eq-2asset-expret","order":{"number":4,"section":[2,1,0,0,0,0,0]}},{"caption":"2.2.3 The Efficient Frontier","key":"sec-frontier","order":{"number":4,"section":[2,2,3,0,0,0,0]}},{"caption":"","key":"eq-cov-defn","order":{"number":1,"section":[2,1,0,0,0,0,0]}},{"caption":"The Efficient Frontier and the Global Minimum Variance Portfolio","key":"fig-frontier-gmv","order":{"number":3,"section":[2,2,3,0,0,0,0]}},{"caption":"2.3.2 Multiple Risky Assets","key":"sec-multiple-cals","order":{"number":8,"section":[2,3,2,0,0,0,0]}},{"caption":"Preferences and the Capital Allocation Line","key":"fig-cal-preferences","order":{"number":11,"section":[2,4,1,0,0,0,0]}},{"caption":"","key":"eq-corr-defn","order":{"number":2,"section":[2,1,0,0,0,0,0]}},{"caption":"2.2.4 Short-Selling","key":"sec-short-frontier","order":{"number":5,"section":[2,2,4,0,0,0,0]}},{"caption":"2.6 Appendix: Portfolios in Excel","key":"sec-excel","order":{"number":11,"section":[2,6,0,0,0,0,0]}},{"caption":"Portfolios of two risky assets","key":"fig-two-asset","order":{"number":1,"section":[2,2,1,0,0,0,0]}},{"caption":"Preferences and Efficient Portfolios","key":"fig-diffsaveborrow-cal-allocation-by-riskaversion","order":{"number":16,"section":[2,4,3,0,0,0,0]}},{"caption":"","key":"eq-diversification-limit","order":{"number":13,"section":[2,2,5,0,0,0,0]}},{"caption":"Preferences and Efficient Portfolios","key":"fig-diffsaveborrow-and-preferences","order":{"number":15,"section":[2,4,3,0,0,0,0]}},{"caption":"","key":"eq-frontier-optimal","order":{"number":19,"section":[2,4,3,0,0,0,0]}},{"caption":"","key":"eq-cal","order":{"number":16,"section":[2,3,1,0,0,0,0]}},{"caption":"","key":"eq-gmv","order":{"number":12,"section":[2,2,3,0,0,0,0]}},{"caption":"Indifference curves with same level of risk aversion","key":"fig-indifference1","order":{"number":10,"section":[2,4,0,0,0,0,0]}},{"caption":"","key":"eq-cal-optimization","order":{"number":17,"section":[2,4,1,0,0,0,0]}},{"caption":"Preferences and Efficient Portfolios","key":"fig-tangency-cal-allocation-by-riskaversion","order":{"number":14,"section":[2,4,2,0,0,0,0]}},{"caption":"","key":"eq-mmult-portvar","order":{"number":9,"section":[2,1,1,0,0,0,0]}},{"caption":"Preferences and Efficient Portfolios","key":"fig-tangency-and-preferences","order":{"number":13,"section":[2,4,2,0,0,0,0]}},{"caption":"","key":"eq-frontier","order":{"number":11,"section":[2,2,3,0,0,0,0]}},{"caption":"","key":"eq-opt-wgt-tangency","order":{"number":18,"section":[2,4,2,0,0,0,0]}},{"caption":"2.2.5 N Risky Assets","key":"sec-n-risky","order":{"number":6,"section":[2,2,5,0,0,0,0]}},{"caption":"Risky asset weight as function of risk aversion","key":"fig-cal-wgt-by-riskaver","order":{"number":12,"section":[2,4,1,0,0,0,0]}},{"caption":"2.3.1 A Single Risky Asset","key":"sec-cal-1risky","order":{"number":7,"section":[2,3,1,0,0,0,0]}},{"caption":"Indifference curves with different levels of risk aversion","key":"fig-indifference0","order":{"number":9,"section":[2,4,0,0,0,0,0]}},{"caption":"","key":"eq-n-asset-return","order":{"number":6,"section":[2,1,1,0,0,0,0]}},{"caption":"2.4 Preferences and Optimal Portfolios","key":"sec-preferences","order":{"number":9,"section":[2,4,0,0,0,0,0]}},{"caption":"Portfolios of three risky assets","key":"fig-three-asset","order":{"number":2,"section":[2,2,2,0,0,0,0]}},{"caption":"2.2.1 Portfolios of Two Risky Assets","key":"sec-two-risky","order":{"number":2,"section":[2,2,1,0,0,0,0]}},{"caption":"Portfolios of three risky assets","key":"fig-diversification","order":{"number":5,"section":[2,2,5,0,0,0,0]}},{"caption":"2.2 Diversification","key":"sec-diversification","order":{"number":1,"section":[2,2,0,0,0,0,0]}},{"caption":"","key":"eq-2asset-variance","order":{"number":5,"section":[2,1,0,0,0,0,0]}},{"caption":"","key":"eq-2asset-variance-corr","order":{"number":10,"section":[2,2,1,0,0,0,0]}},{"caption":"Short-Selling and the Frontier","key":"fig-frontier-gmv-shorting","order":{"number":4,"section":[2,2,4,0,0,0,0]}},{"caption":"Capital Allocation Line","key":"fig-cal","order":{"number":6,"section":[2,3,1,0,0,0,0]}},{"caption":"2.2.2 Three Risky Assets","key":"sec-three-risky","order":{"number":3,"section":[2,2,2,0,0,0,0]}},{"caption":"Tangency portfolio of two risky assets","key":"fig-two-asset-plus_rf","order":{"number":7,"section":[2,3,2,0,0,0,0]}},{"caption":"","key":"eq-sd-rf-risky","order":{"number":14,"section":[2,3,1,0,0,0,0]}}],"headings":["portfolio-statistics","two-asset-portfolios","portfolios-of-n-assets","sec-diversification","sec-two-risky","sec-three-risky","sec-frontier","sec-short-frontier","sec-n-risky","capital-allocation-to-risky-assets","sec-cal-1risky","sec-multiple-cals","sec-preferences","a-single-risky-asset-cal","the-tangency-cal","capital-allocation-with-differential-borrowing-lending-rates","sec-portfolio-class","sec-excel"]}